kryoip/__init__.py
kryoip-6.post4.dist-info/METADATA
kryoip-6.post4.dist-info/WHEEL
kryoip-6.post4.dist-info/top_level.txt
kryoip-6.post4.dist-info/RECORD
